z_agent/__init__.py
z_agent/cli.py
z_agent/web_sockets.py
z_agent-0.1.0.10.dist-info/LICENSE
z_agent-0.1.0.10.dist-info/METADATA
z_agent-0.1.0.10.dist-info/WHEEL
z_agent-0.1.0.10.dist-info/entry_points.txt
z_agent-0.1.0.10.dist-info/top_level.txt
z_agent-0.1.0.10.dist-info/RECORD
